viennaps/__init__.pyi
viennaps/__init__.py
viennaps/_core.cpython-311-x86_64-linux-gnu.so
viennaps/_core/__init__.pyi
viennaps/_core/gpu.pyi
viennaps/_core/constants.pyi
viennaps/_core/util.pyi
viennaps/d2/__init__.pyi
viennaps/d2/gpu.pyi
viennaps/d3/__init__.pyi
viennaps/d3/gpu.pyi
viennaps-4.2.1.dist-info/WHEEL
viennaps-4.2.1.dist-info/METADATA
viennaps-4.2.1.dist-info/RECORD
viennaps-4.2.1.dist-info/licenses/LICENSE
viennaps.libs/embree-vars.sh
viennaps.libs/libvtkFiltersHyperTree-9.3.so
viennaps.libs/embree-config-version.cmake
viennaps.libs/embree-vars.csh
viennaps.libs/libvtkParallelCore-9.3.so
viennaps.libs/libvtkIOXMLParser-9.3.so
viennaps.libs/libvtkjpeg-9.3.so
viennaps.libs/liblexers.a
viennaps.libs/libvtkfreetype-9.3.so
viennaps.libs/libGLdispatch-dcc1ca97.so.0.0.0
viennaps.libs/libmath.a
viennaps.libs/libvtkFiltersStatistics-9.3.so
viennaps.libs/libvtkkissfft-9.3.so
viennaps.libs/libvtkRenderingUI-9.3.so
viennaps.libs/libvtkdoubleconversion-9.3.so
viennaps.libs/libvtkCommonCore-9.3.so
viennaps.libs/libvtkCommonExecutionModel-9.3.so
viennaps.libs/libvtksys-9.3.so
viennaps.libs/libvtklzma-9.3.so
viennaps.libs/libsimd.a
viennaps.libs/libvtkCommonColor-9.3.so
viennaps.libs/libvtkInteractionStyle-9.3.so
viennaps.libs/libvtkexpat-9.3.so
viennaps.libs/libvtkpugixml-9.3.so
viennaps.libs/embree-config.cmake
viennaps.libs/uninstall.cmake
viennaps.libs/libgomp-a34b3233.so.1.0.0
viennaps.libs/libembree_sse42.a
viennaps.libs/libvtkFiltersExtraction-9.3.so
viennaps.libs/libvtkParallelDIY-9.3.so
viennaps.libs/libvtkIOCore-9.3.so
viennaps.libs/libvtkFiltersGeometry-9.3.so
viennaps.libs/libvtkCommonSystem-9.3.so
viennaps.libs/libOpenGL-b706661f.so.0.0.0
viennaps.libs/libvtkmetaio-9.3.so
viennaps.libs/libvtkRenderingOpenGL2-9.3.so
viennaps.libs/libvtkzlib-9.3.so
viennaps.libs/libvtkCommonMisc-9.3.so
viennaps.libs/libvtkCommonMath-9.3.so
viennaps.libs/libvtkfmt-9.3.so
viennaps.libs/libembree4.so
viennaps.libs/cmake_install.cmake
viennaps.libs/libvtkFiltersHybrid-9.3.so
viennaps.libs/libvtkFiltersGeneral-9.3.so
viennaps.libs/libvtkglew-9.3.so
