Metadata-Version: 2.2
Name: ViennaPS
Version: 4.2.1
Summary: Topography simulation library for microelectronic fabrication processes
License: Copyright (c) 2025      Institute for Microelectronics, TU Wien.
Project-URL: Homepage, https://viennatools.github.io/ViennaPS/
Project-URL: Documentation, https://viennatools.github.io/ViennaPS/
Project-URL: Repository, https://github.com/ViennaTools/ViennaPS
Project-URL: Issues, https://github.com/ViennaTools/ViennaPS/issues
Requires-Dist: ViennaLS>=5.5.0
